{
 "attach_print": 0,
 "channel": "System Notification",
 "creation": "2024-08-08 12:18:27.639383",
 "date_changed": "insurance_expiry",
 "days_in_advance": 3,
 "docstatus": 0,
 "doctype": "Notification",
 "document_type": "Vehicle",
 "enabled": 1,
 "event": "Days Before",
 "idx": 0,
 "is_standard": 1,
 "message": "<p>The insurance will be expired in the next 3 days</p>\n",
 "message_type": "Markdown",
 "modified": "2024-08-08 12:22:33.154623",
 "modified_by": "Administrator",
 "module": "Rentals",
 "name": "Insurance Expiry Reminder",
 "owner": "Administrator",
 "recipients": [
  {
   "receiver_by_role": "System Manager"
  }
 ],
 "send_system_notification": 0,
 "send_to_all_assignees": 0,
 "subject": "Insurance for {{ doc.title }} expiring in 3 days!"
}